{
  "app.tagline": "Limpieza honesta del sistema · Código abierto · sin telemetría",

  "titlebar.minimize": "Minimizar",
  "titlebar.maximize": "Maximizar",
  "titlebar.close": "Cerrar",

  "sidebar.navigation": "NAVEGACIÓN",
  "sidebar.language": "Idioma",
  "sidebar.version": "v1.1.0 · Código abierto",
  "theme.toggleTooltip": "Cambiar el diseño entre claro y oscuro",
  "theme.dark": "🌙 Oscuro",
  "theme.light": "☀ Claro",

  "nav.overview": "Resumen",
  "nav.storage": "Almacenamiento y RAM",
  "nav.cleaner": "Limpieza",
  "nav.startup": "Inicio",
  "nav.privacy": "Privacidad",
  "nav.updates": "Actualizaciones",
  "nav.schedule": "Programación",
  "nav.uninstall": "Desinstalar",
  "nav.duplicates": "Duplicados",

  "common.refresh": "Actualizar",
  "common.clean": "Limpiar",
  "common.analyze": "Analizar",
  "common.selectAll": "Seleccionar todo",
  "common.deselectAll": "Deseleccionar todo",
  "common.all": "Todos",
  "common.notAnalyzed": "Aún no analizado.",
  "common.includeInAnalysis": "Incluir en el análisis",

  "dashboard.title": "Resumen",
  "dashboard.subtitle": "Una mirada honesta a tu sistema: solo mediciones reales.",
  "dashboard.loadingBanner": "Cargando datos en segundo plano …",
  "dashboard.tile.score": "PUNTUACIÓN GLOBAL",
  "dashboard.tile.ram": "USO DE RAM",
  "dashboard.tile.storage": "ESPACIO EN DISCO",
  "dashboard.tile.startup": "INICIO",
  "dashboard.tile.reclaimable": "RECUPERABLE",
  "dashboard.scorePerfect": "100/100 – sin penalizaciones.",
  "dashboard.driveCount": "{0} unidad(es)",
  "dashboard.viewDetails": "Ver detalles",
  "dashboard.openStartup": "Abrir inicio",
  "dashboard.recommendations": "Recomendaciones",

  "dashboard.status.preparing": "Preparando el análisis …",
  "dashboard.status.analyzing": "Analizando el sistema (tamaño de temp/caché, inicio, unidades) …",
  "dashboard.status.done": "Análisis completado · Puntuación {0}/100 ({1}).",

  "dashboard.ram.summary": "{0} de {1} en uso · {2} libres",
  "dashboard.ram.unavailable": "Uso de RAM no disponible.",
  "dashboard.drives.none": "No se encontraron unidades fijas.",
  "dashboard.drives.summary": "{0} unidad(es) · {1} de {2} libres",
  "dashboard.startup.summary": "{0} activos · {1} con alto impacto en el inicio",
  "dashboard.temp.summary": "{0} recuperables en {1} elemento(s)",

  "score.good": "Bien",
  "score.improvable": "Mejorable",
  "score.critical": "Crítico",
  "score.explanation.factors": "Estos factores restaron puntos:",
  "score.explanation.clean": "No se encontraron problemas medibles: todo en orden.",
  "score.factor.driveCritical": "Unidad {0} solo {1} % libre (crítico)",
  "score.factor.driveLow": "Unidad {0} solo {1} % libre (escaso)",
  "score.factor.reclaimable": "{0} recuperables (temp/caché)",
  "score.factor.startupActive": "{0} programas de inicio activos",
  "score.factor.startupHigh": "{0} de inicio con alto impacto",
  "score.factor.ramLoad": "Uso de RAM {0} %",

  "reco.reclaimable.title": "{0} recuperables",
  "reco.reclaimable.text": "Se pueden liberar {0} archivos temporales / cachés.",
  "reco.driveFull.title": "La unidad {0} está al {1} % de uso",
  "reco.driveFull.text": "Solo quedan {0} libres. Limpiar libera espacio al instante.",
  "reco.startup.title": "{0} programas de inicio activos",
  "reco.startup.textHigh": "{0} de ellos con alto impacto: desactivarlos puede acelerar el arranque.",
  "reco.startup.textMany": "Muchos programas se inician con Windows: revisa lo que realmente necesitas.",
  "reco.ram.title": "Uso alto de RAM ({0} %)",
  "reco.ram.text": "Solo información: cierra los programas que no necesites. OpenClean no «libera» memoria.",
  "reco.allGood.title": "Todo en orden",
  "reco.allGood.text": "No se encontraron problemas medibles. Tu sistema está limpio y bien aprovechado.",
  "dashboard.runAll": "Ejecutar todo",
  "reco.startup.text": "Reduce el tiempo de inicio — {0} programas con alto impacto de arranque.",
  "reco.tag.critical": "Crítico",
  "reco.tag.recommended": "Recomendado",
  "reco.tag.hint": "Aviso",
  "reco.tag.good": "Óptimo",
  "reco.unit.free": "libre",
  "reco.unit.reclaimable": "recuperable",
  "reco.unit.active": "activos",
  "reco.unit.load": "uso",
  "reco.action.check": "Revisar",
  "reco.action.view": "Ver",

  "system.title": "Almacenamiento y RAM",
  "system.subtitle": "Vista detallada: pura información, sin «optimización» ni «acelerador de RAM».",
  "system.ramHeading": "MEMORIA (RAM)",
  "system.ramLoad": "Uso",
  "system.used": "En uso: ",
  "system.free": "Libre: ",
  "system.total": "Total: ",
  "system.drives": "Unidades",
  "system.drive.summary": "{0} de {1} en uso · {2} libres",
  "system.drive.warnCritical": "Crítico – solo {0} % libre",
  "system.drive.warnLow": "Escaso – solo {0} % libre",

  "startup.title": "Inicio",
  "startup.subtitle": "Programas que arrancan con Windows. Desactiva lo que no necesites.",
  "startup.filter.all": "Todos",
  "startup.filter.enabled": "Activados",
  "startup.filter.disabled": "Desactivados",
  "startup.col.program": "PROGRAMA",
  "startup.col.publisher": "EDITOR",
  "startup.col.origin": "ORIGEN",
  "startup.col.impact": "IMPACTO DE INICIO",
  "startup.col.status": "ESTADO",
  "startup.policyTooltip": "Establecido por directiva de grupo: no se puede cambiar con OpenClean",
  "startup.taskSchedulerNote": "Nota: las entradas del Programador de tareas no se muestran por ahora.",
  "startup.status.loading": "Cargando programas de inicio …",
  "startup.status.none": "No se encontraron entradas de inicio.",
  "startup.status.summary": "{0} programa(s) de inicio. {1} activados.",
  "startup.error.changeFailed": "No se pudo cambiar «{0}»: {1}",

  "startup.impact.high": "Alto",
  "startup.impact.medium": "Medio",
  "startup.impact.low": "Bajo",
  "startup.impact.unknown": "Desconocido",
  "startup.impact.estimated": "~{0} (estimado)",
  "startup.state.enabled": "Activado",
  "startup.state.disabled": "Desactivado",
  "startup.state.once": "Una vez",
  "startup.state.policy": "Directiva",
  "startup.publisher.unknown": "Desconocido",

  "startup.location.hkcuRun": "Registro (usuario actual)",
  "startup.location.hklmRun": "Registro (todos los usuarios)",
  "startup.location.hklmRunWow": "Registro (todos los usuarios, 32 bits)",
  "startup.location.hkcuRunOnce": "Registro (usuario actual, RunOnce)",
  "startup.location.hklmRunOnce": "Registro (todos los usuarios, RunOnce)",
  "startup.location.hklmPolicies": "Registro (directiva, todos los usuarios)",
  "startup.location.hkcuPolicies": "Registro (directiva, usuario actual)",
  "startup.location.packaged": "Aplicación de la Store (UWP)",
  "startup.location.folderUser": "Carpeta de inicio (usuario)",
  "startup.location.folderCommon": "Carpeta de inicio (todos los usuarios)",
  "startup.error.noTaskKey": "No se conoce ninguna clave de tarea para esta aplicación de la Store.",
  "startup.error.taskKeyMissing": "No se encontró la clave de tarea de la aplicación de la Store.",

  "updater.title": "Actualizaciones de software",
  "updater.subtitle": "Actualiza programas obsoletos mediante winget: tú decides qué se actualiza.",
  "updater.col.program": "PROGRAMA",
  "updater.col.id": "ID",
  "updater.col.current": "ACTUAL",
  "updater.col.available": "DISPONIBLE",
  "updater.col.action": "ACCIÓN",
  "updater.action.update": "Actualizar",
  "updater.action.updateAll": "Actualizar todo",
  "updater.status.loading": "Buscando actualizaciones …",
  "updater.status.none": "Todos los programas están actualizados.",
  "updater.status.summary": "{0} actualización(es) disponible(s).",
  "updater.status.wingetMissing": "No se encontró winget. Instala el «Instalador de aplicaciones» desde Microsoft Store para usar las actualizaciones.",
  "updater.status.updating": "Actualizando {0} …",
  "updater.status.updatingAll": "Actualizando {0}/{1}: {2} …",
  "updater.confirm.title": "Confirmar actualización",
  "updater.confirm.single": "«{0}» se actualizará de la versión {1} a la {2}.\n\n¿Quieres continuar?",
  "updater.confirm.all": "Se actualizarán {0} programa(s) mediante winget.\n\n¿Quieres continuar?",
  "updater.done.single": "«{0}» se ha actualizado.",
  "updater.done.all": "Se actualizaron {0} de {1} programa(s).",
  "updater.error.failed": "No se pudo actualizar «{0}»: {1}",

  "cleaner.title": "Limpieza",
  "cleaner.subtitle": "Vista previa antes de borrar: tú decides qué se elimina.",
  "cleaner.selectedLabel": "Seleccionado para limpiar",
  "cleaner.objects": "Objetos",
  "cleaner.emptyPreview": "No se encontraron archivos: tras analizar aparecerán aquí los objetos.",
  "cleaner.header.withItems": "{0} — {1}/{2} archivos, {3}",
  "cleaner.subheader.withItems": "{0} — {1}/{2} archivos, {3}",
  "cleaner.status.ready": "Listo. Haz clic en «Analizar» para ver qué se puede limpiar.",
  "cleaner.status.scanning": "Analizando directorios temporales y de caché …",
  "cleaner.status.preparing": "Preparando el análisis …",
  "cleaner.status.doneSelectable": "Análisis completado. Revisa la lista y haz clic en «Limpiar».",
  "cleaner.status.doneEmpty": "Análisis completado: no se encontró nada que limpiar.",
  "cleaner.progress.analyzing": "Analizando …",
  "cleaner.progress.analyzingPath": "Analizando: {0}",
  "cleaner.progress.deleting": "Borrando …",
  "cleaner.progress.deletingPath": "Borrando: {0}",
  "cleaner.eta.remaining": "aprox. {0} restante",
  "cleaner.selection.summary": "{0} objeto(s) seleccionados · se liberarán {1}",
  "cleaner.confirm.preparing": "Preparando la limpieza …",
  "cleaner.confirm.message": "Se borrarán permanentemente {0} objeto(s) con un total de {1}.\n\n¿Quieres continuar?",
  "cleaner.report": "{0} objeto(s) borrados · {1} liberados",
  "cleaner.report.skipped": " · {0} omitidos",

  "privacy.title": "Privacidad",
  "privacy.subtitle": "Vista previa antes de borrar: tú decides qué rastros se eliminan.",
  "privacy.selectedLabel": "Seleccionado para limpiar",
  "privacy.entries": "Entradas",
  "privacy.emptyPreview": "No se encontraron entradas: tras analizar aparecerán aquí los rastros.",
  "privacy.header.withItems": "{0} — {1}/{2} seleccionados",
  "privacy.status.ready": "Listo. Haz clic en «Analizar» para ver qué rastros se pueden eliminar.",
  "privacy.status.scanning": "Analizando rastros de privacidad …",
  "privacy.status.cleaning": "Limpiando …",
  "privacy.status.doneSelectable": "Análisis completado. Revisa la lista y haz clic en «Limpiar».",
  "privacy.status.doneEmpty": "Análisis completado: no se encontraron rastros eliminables.",
  "privacy.status.cleaned": "Limpieza completada.",
  "privacy.selection.summary": "{0} entrada(s) seleccionadas",
  "privacy.report.line": "{0}: {1} borradas",
  "privacy.report.total": "{0} entrada(s) borradas · {1}",
  "privacy.confirm.intro": "Se borrarán permanentemente {0} entrada(s) de las siguientes categorías:\n",
  "privacy.confirm.categoryLine": "\n• {0}: {1}",
  "privacy.confirm.cookieWarning": "\n\n⚠ ATENCIÓN: Se eliminarán las cookies incluidas. Se cerrará tu sesión en los sitios afectados y tendrás que volver a iniciar sesión.",
  "privacy.confirm.proceed": "\n\n¿Quieres continuar?",

  "privacy.browserHistory.name": "Historial del navegador",
  "privacy.browserHistory.description": "Páginas web visitadas recientemente en Chrome, Edge, Brave y Firefox.",
  "privacy.cookies.name": "Cookies",
  "privacy.cookies.description": "Cookies almacenadas por sitio web: borrarlas cierra las sesiones activas.",
  "privacy.recentFiles.name": "Archivos usados recientemente",
  "privacy.recentFiles.description": "La lista de archivos y carpetas abiertos recientemente (Windows Recent).",
  "privacy.officeMru.name": "Historial de Office",
  "privacy.officeMru.description": "Documentos abiertos recientemente en Word, Excel y PowerPoint (MRU).",
  "privacy.explorerSearch.name": "Historial de búsqueda del Explorador",
  "privacy.explorerSearch.description": "Términos buscados recientemente en el Explorador de archivos.",
  "privacy.startMenuSearch.name": "Historial de búsqueda del menú Inicio",
  "privacy.startMenuSearch.description": "Términos escritos recientemente en la búsqueda de Windows.",
  "privacy.clipboard.name": "Portapapeles",
  "privacy.clipboard.description": "El contenido actual del portapapeles de Windows.",
  "privacy.clipboard.itemName": "Contenido del portapapeles",
  "privacy.mediaPlayer.name": "Historial del reproductor multimedia",
  "privacy.mediaPlayer.description": "Medios reproducidos recientemente en VLC media player y Windows Media Player.",

  "confirm.title": "Confirmar limpieza",
  "confirm.cancel": "Cancelar",
  "confirm.confirm": "Limpiar",

  "cleanup.recycleBin.progress": "Papelera de reciclaje …",
  "cleanup.recycleBin.name": "Papelera de reciclaje",
  "cleanup.recycleBin.itemPath": "Papelera de reciclaje (todas las unidades)",
  "cleanup.report.summary": "{0} objeto(s) borrados, {1} liberados.",
  "cleanup.report.skipped": " {0} omitidos (en uso / sin acceso).",

  "cat.windowsTemp.name": "Temp de Windows",
  "cat.windowsTemp.description": "Archivos temporales de Windows y programas (%TEMP%, C:\\Windows\\Temp).",
  "cat.updateCache.name": "Caché de Windows Update",
  "cat.updateCache.description": "Descargas de actualizaciones ya instaladas (SoftwareDistribution\\Download). Requiere admin.",
  "cat.thumbnails.name": "Caché de miniaturas",
  "cat.thumbnails.description": "Bases de datos de miniaturas del Explorador (thumbcache_*.db). Se reconstruyen.",
  "cat.chrome.name": "Google Chrome",
  "cat.chrome.description": "Contenido web en caché de Google Chrome (todos los perfiles).",
  "cat.edge.name": "Microsoft Edge",
  "cat.edge.description": "Contenido web en caché de Microsoft Edge (todos los perfiles).",
  "cat.brave.name": "Brave",
  "cat.brave.description": "Contenido web en caché de Brave (todos los perfiles).",
  "cat.firefox.name": "Mozilla Firefox",
  "cat.firefox.description": "Contenido web en caché de Mozilla Firefox (todos los perfiles).",
  "cat.inetCache.name": "Caché de Internet (heredada/WinINet)",
  "cat.inetCache.description": "Caché de WinINet/IE (%LocalAppData%\\Microsoft\\Windows\\INetCache).",
  "cat.appCache.name": "Cachés de apps (AppData)",
  "cat.appCache.description": "Carpetas de caché conocidas de apps instaladas en %AppData% y %LocalAppData%.",
  "cat.recycleBin.name": "Papelera de reciclaje",
  "cat.recycleBin.description": "Vacía la papelera de reciclaje de todas las unidades mediante el shell de Windows.",

  "sub.browserCache.name": "Caché",
  "sub.codeCache.name": "Caché de código",
  "sub.userTemp.name": "Temp. de usuario",
  "sub.windowsTemp.name": "Temp. de Windows",
  "sub.thumbCache.name": "Caché de miniaturas",
  "sub.iconCache.name": "Caché de iconos",
  "sub.files.name": "Archivos",

  "schedule.title": "Limpieza programada",
  "schedule.subtitle": "Limpieza automática según un horario: se ejecuta mediante una tarea de Windows, sin servicio en segundo plano.",
  "schedule.action.runNow": "Ejecutar ahora",
  "schedule.action.apply": "Aplicar",
  "schedule.warning.title": "La limpieza automática borra SIN preguntar",
  "schedule.warning.body": "En una ejecución programada NO se muestra ninguna confirmación NI vista previa. Todos los objetos de las categorías seleccionadas se eliminan de forma definitiva sin preguntar. Activa la automatización solo si estás de acuerdo con ello.",
  "schedule.enable.label": "Activar limpieza automática",
  "schedule.enable.hint": "Crea una tarea de Windows que inicia OpenClean a la hora elegida con los máximos permisos y limpia de forma silenciosa. Sin activarla, no se programa nada.",
  "schedule.section.when": "CUÁNDO SE LIMPIA",
  "schedule.freq.daily": "Diariamente",
  "schedule.freq.weekly": "Semanalmente",
  "schedule.freq.monthly": "Mensualmente",
  "schedule.time.label": "Hora",
  "schedule.weekday.label": "Día de la semana",
  "schedule.dayOfMonth.label": "Día del mes",
  "schedule.weekday.mon": "Lunes",
  "schedule.weekday.tue": "Martes",
  "schedule.weekday.wed": "Miércoles",
  "schedule.weekday.thu": "Jueves",
  "schedule.weekday.fri": "Viernes",
  "schedule.weekday.sat": "Sábado",
  "schedule.weekday.sun": "Domingo",
  "schedule.section.what": "QUÉ SE LIMPIA",
  "schedule.profile.tempOnly": "Solo Temp",
  "schedule.profile.tempOnly.hint": "Temp de Windows, caché de actualizaciones, miniaturas y caché de Internet: el alcance con menos riesgo.",
  "schedule.profile.full": "Completo",
  "schedule.profile.full.hint": "Todas las categorías disponibles, incluidas las cachés del navegador y la papelera de reciclaje.",
  "schedule.profile.custom": "Personalizado",
  "schedule.profile.custom.hint": "Elige tú mismo qué categorías se limpian automáticamente.",
  "schedule.notify.label": "Mostrar notificación",
  "schedule.notify.hint": "Muestra una breve notificación de Windows con el resultado tras una limpieza automática.",
  "schedule.section.reportsave": "GUARDADO DE INFORMES",
  "schedule.reportsave.label": "Guardar informes",
  "schedule.reportsave.hint": "Guarda un informe tras cada limpieza automática (historial en la interfaz y registro de texto) en el directorio de datos.",
  "schedule.reportsave.retention.label": "Retención",
  "schedule.profile.badge.recommended": "RECOMENDADO",
  "schedule.profile.badge.risk": "RIESGO",
  "schedule.reports.heading": "Informes",
  "schedule.reports.empty": "Aún no se ha realizado ninguna limpieza automática.",
  "schedule.report.deletedHeading": "OBJETOS BORRADOS",
  "schedule.report.summary": "{0} objeto(s) borrados · {1} liberados",
  "schedule.report.skipped": " · {0} omitidos",
  "schedule.report.truncated": "Solo se guardan las primeras entradas: se borraron más objetos de los que se enumeran aquí.",
  "schedule.status.applying": "Configurando la tarea …",
  "schedule.status.registered": "La limpieza automática está activa (tarea programada de Windows creada).",
  "schedule.status.disabled": "Limpieza automática desactivada: tarea programada eliminada.",
  "schedule.status.inactive": "La limpieza automática no está activa.",
  "schedule.status.error": "No se pudo modificar la tarea programada. ¿OpenClean se ejecuta como administrador?",
  "schedule.status.runError": "No se pudo completar la limpieza. Inténtalo de nuevo.",
  "schedule.status.running": "Limpieza en curso …",
  "schedule.status.ranNow": "Limpieza completada: {0} objeto(s) borrados · {1} liberados.",
  "schedule.runNow.confirm": "La limpieza se ejecutará ahora con el perfil seleccionado y borrará de forma definitiva los objetos encontrados, sin más vista previa.\n\n¿Quieres continuar?",
  "schedule.runNow.title": "Limpiar ahora",
  "schedule.runNow.action": "Limpiar",
  "schedule.toast.title": "OpenClean – Limpieza completada",
  "schedule.toast.body": "{0} objeto(s) borrados · {1} liberados.",
  "uninstall.title": "Desinstalación",
  "uninstall.subtitle": "Elimina a fondo los programas instalados: con tamaño, desinstalación por lotes y limpieza de residuos.",
  "uninstall.searchPlaceholder": "Buscar programa …",
  "uninstall.sort.size": "Tamaño",
  "uninstall.sort.name": "Nombre",
  "uninstall.action.uninstall": "Desinstalar",
  "uninstall.action.uninstallSelected": "Desinstalar seleccionados",
  "uninstall.col.program": "PROGRAMA",
  "uninstall.col.version": "VERSIÓN",
  "uninstall.col.size": "TAMAÑO",
  "uninstall.big": "GRANDE",
  "uninstall.col.action": "ACCIÓN",
  "uninstall.publisher.unknown": "Desconocido",
  "uninstall.status.loading": "Cargando los programas instalados …",
  "uninstall.status.none": "No se encontraron programas instalados.",
  "uninstall.status.summary": "{0} programa(s) instalado(s).",
  "uninstall.status.uninstalling": "Desinstalando {0} …",
  "uninstall.status.uninstallingBatch": "Desinstalando {0}/{1}: {2} …",
  "uninstall.status.doneSingle": "«{0}» desinstalado.",
  "uninstall.status.failedSingle": "No se pudo desinstalar «{0}».",
  "uninstall.status.doneBatch": "{0} programa(s) procesado(s).",
  "uninstall.selection.summary": "{0} seleccionado(s) · {1}",
  "uninstall.confirm.title": "Confirmar desinstalación",
  "uninstall.confirm.single": "«{0}» se desinstalará. Se iniciará el desinstalador del fabricante.\n\n¿Quieres continuar?",
  "uninstall.confirm.batch": "{0} programa(s) se desinstalarán uno tras otro, de forma silenciosa si es posible.\n\n¿Quieres continuar?",
  "uninstall.leftover.heading": "Se encontraron residuos de {0}",
  "uninstall.leftover.multiple": "{0} programas",
  "uninstall.leftover.hint": "Estas carpetas y claves del registro quedaron atrás. Revisa la selección: no se borrará nada hasta que lo confirmes.",
  "uninstall.leftover.folder": "CARPETA",
  "uninstall.leftover.registry": "REGISTRO",
  "uninstall.leftover.ignore": "Ignorar",
  "uninstall.leftover.action": "Eliminar residuos",
  "uninstall.leftover.confirmTitle": "Eliminar residuos",
  "uninstall.leftover.confirm": "{0} residuo(s) con un total de {1} se borrarán de forma definitiva.\n\n¿Quieres continuar?",
  "uninstall.leftover.removing": "Eliminando residuos …",
  "uninstall.leftover.done": "{0} residuo(s) eliminado(s) · {1} liberados.",

  "duplicates.title": "Duplicados",
  "duplicates.subtitle": "Encuentra duplicados exactos (SHA-256) y elimina copias redundantes de forma segura",
  "duplicates.folders.heading": "CARPETAS A ANALIZAR",
  "duplicates.folders.empty": "Aún no hay carpetas seleccionadas – usa «Añadir carpeta» para añadir una o varias carpetas.",
  "duplicates.action.addFolder": "Añadir carpeta",
  "duplicates.action.removeFolder": "Quitar carpeta",
  "duplicates.action.scan": "Iniciar análisis",
  "duplicates.action.cancel": "Cancelar",
  "duplicates.action.delete": "Borrar marcados",
  "duplicates.autoselect.label": "Selección automática:",
  "duplicates.autoselect.keepNewest": "Conservar el más reciente",
  "duplicates.autoselect.keepOldest": "Conservar el más antiguo",
  "duplicates.autoselect.keepShortestPath": "Conservar la ruta más corta",
  "duplicates.autoselect.clear": "Limpiar selección",
  "duplicates.groups.heading": "GRUPOS DE DUPLICADOS",
  "duplicates.group.summary": "{0} copias · {1} cada una",
  "duplicates.compare.heading": "COMPARAR COPIAS – MARCA LO QUE SE DEBE BORRAR",
  "duplicates.compare.empty": "Selecciona un grupo de duplicados a la izquierda para comparar sus copias lado a lado.",
  "duplicates.file.size": "Tamaño",
  "duplicates.file.modified": "Modificado",
  "duplicates.file.created": "Creado",
  "duplicates.file.deleteThis": "Borrar esta copia",
  "duplicates.selection.summary": "{0} copia(s) marcadas · {1}",
  "duplicates.status.idle": "Selecciona carpetas e inicia un análisis para encontrar duplicados.",
  "duplicates.status.collecting": "Recopilando archivos … ({0})",
  "duplicates.status.hashing": "Comparando contenidos … ({0}/{1})",
  "duplicates.status.none": "No se encontraron duplicados.",
  "duplicates.status.cancelled": "Análisis cancelado.",
  "duplicates.status.summary": "{0} grupo(s) con {1} archivo(s) encontrados · {2} desperdiciados.",
  "duplicates.status.deleting": "Borrando las copias marcadas …",
  "duplicates.status.deleted": "{0} copia(s) borradas · {1} liberados.",
  "duplicates.status.skipped": " {0} omitidas (bloqueadas o última copia).",
  "duplicates.confirm.title": "Borrar duplicados",
  "duplicates.confirm.body": "{0} copia(s) marcadas con un total de {1} se borrarán de forma definitiva.\nSiempre se conserva al menos una copia por grupo.\n\n¿Quieres continuar?",

  "error.unexpected": "Error inesperado: {0}",

  "premium.locked.title": "Función Premium",
  "premium.locked.schedule.pitch": "La limpieza automática programada ordena tu PC regularmente en segundo plano: diaria, semanal o mensualmente, con un perfil de limpieza configurable e informes de cada ejecución.",
  "premium.locked.body": "Esta función forma parte de OpenClean Premium (pago único, sin suscripción). Con tu compra apoyas el desarrollo: el núcleo de OpenClean sigue siendo gratuito y de código abierto.",
  "premium.locked.grandfathered.title": "Tu programación existente sigue funcionando",
  "premium.locked.grandfathered.body": "Ya usabas la limpieza programada antes de la introducción de Premium. Tu programación configurada sigue activa y limpiando automáticamente. Para cambiar su configuración se necesita Premium.",
  "premium.locked.disableSchedule": "Desactivar programación",
  "premium.locked.scheduleDisabled": "La programación se ha desactivado y la tarea programada se ha eliminado.",
  "premium.action.buy": "Comprar Premium",
  "premium.action.activate": "Activar licencia",
  "premium.activate.title": "Activar licencia",
  "premium.activate.hint": "Introduce la clave de licencia que recibiste por correo tras la compra (OPENCLEAN-XXXX-XXXX-XXXX-XXXX).",
  "premium.activate.privacy": "Al activar solo se transmiten: la clave de licencia, un hash anónimo del dispositivo y la versión de la app. Sin telemetría, sin cuenta.",
  "premium.activate.action": "Activar",
  "premium.activate.working": "Activando licencia …",
  "premium.activate.success": "Licencia activada: Premium está desbloqueado.",
  "premium.activate.downloadingModule": "Descargando el módulo Premium …",
  "premium.error.invalidKey": "La clave de licencia no es válida o ha sido revocada.",
  "premium.error.deviceLimit": "Límite de dispositivos alcanzado: esta licencia ya está activa en el número máximo de dispositivos. Desactiva primero otro dispositivo.",
  "premium.error.network": "El servidor de licencias no está disponible en este momento. Comprueba tu conexión a internet e inténtalo de nuevo.",
  "premium.error.rateLimited": "Demasiadas solicitudes en poco tiempo. Espera un momento e inténtalo de nuevo.",
  "premium.error.moduleLoad": "No se pudo cargar el módulo Premium. Inténtalo de nuevo.",
  "premium.module.missingTitle": "Falta el módulo Premium",
  "premium.module.missingBody": "Tu licencia es válida, pero el módulo Premium falta o está dañado en este dispositivo. Puede descargarse de nuevo ahora.",
  "premium.module.retry": "Descargar módulo de nuevo",
  "premium.batch.locked": "Desinstalar varios programas a la vez es una función Premium. Puedes seguir desinstalando programas individuales gratis.",
  "schedule.auto.skippedNoLicense": "Limpieza programada omitida: no hay licencia Premium activa."
}
